docker_files_generator/__init__.py
docker_files_generator/github_repo_files.py
docker_files_generator/main.py
docker_files_generator/prompt.py
chatgpt_docker_files_generator-0.2.0.dist-info/LICENSE
chatgpt_docker_files_generator-0.2.0.dist-info/METADATA
chatgpt_docker_files_generator-0.2.0.dist-info/WHEEL
chatgpt_docker_files_generator-0.2.0.dist-info/top_level.txt
chatgpt_docker_files_generator-0.2.0.dist-info/RECORD
