Metadata-Version: 2.1
Name: chatgpt-docker-files-generator
Version: 0.2.0
Summary: ChatGPT docker files generator.
Home-page: https://github.com/Tsyhanok-Ivan/chatgpt-docker-files-generator
Author: tsyhanok-ivan
Keywords: docker chatgpt python generator dockerfile
Classifier: Programming Language :: Python :: 3.10
Classifier: License :: OSI Approved :: MIT License
Classifier: Operating System :: OS Independent
Requires-Python: >=3.0
License-File: LICENSE
Requires-Dist: requests ==2.32.3
Requires-Dist: openai ==1.63.2
